lektor_algolia.py
lektor_algolia-0.0.4.dist-info/DESCRIPTION.rst
lektor_algolia-0.0.4.dist-info/METADATA
lektor_algolia-0.0.4.dist-info/RECORD
lektor_algolia-0.0.4.dist-info/WHEEL
lektor_algolia-0.0.4.dist-info/entry_points.txt
lektor_algolia-0.0.4.dist-info/metadata.json
lektor_algolia-0.0.4.dist-info/top_level.txt
