Metadata-Version: 2.0
Name: lektor-algolia
Version: 0.0.4
Summary: Lektor plugin to support generating an Algolia search index from your data
Home-page: https://github.com/sherbondy/lektor-algolia
Author: Ethan Sherbondy
Author-email: sherbondye@gmail.com
License: MIT
Platform: UNKNOWN
Requires-Dist: Lektor
Requires-Dist: algoliasearch (>=1.7.1)
